restpki_ng_python_client/__init__.py
restpki_ng_python_client/api_client.py
restpki_ng_python_client/api_response.py
restpki_ng_python_client/configuration.py
restpki_ng_python_client/exceptions.py
restpki_ng_python_client/file_utils.py
restpki_ng_python_client/py.typed
restpki_ng_python_client/rest.py
restpki_ng_python_client/restpki_ng_client.py
restpki_ng_python_client/standard_signature_policies.py
restpki_ng_python_client/utils.py
restpki_ng_python_client/api/__init__.py
restpki_ng_python_client/api/authentication_api.py
restpki_ng_python_client/api/cades_signature_api.py
restpki_ng_python_client/api/document_keys_api.py
restpki_ng_python_client/api/documents_api.py
restpki_ng_python_client/api/pades_signature_api.py
restpki_ng_python_client/api/pades_visual_positioning_presets_api.py
restpki_ng_python_client/api/pdf_api.py
restpki_ng_python_client/api/signature_api.py
restpki_ng_python_client/api/signature_inspection_api.py
restpki_ng_python_client/api/signature_sessions_api.py
restpki_ng_python_client/api/timestamp_api.py
restpki_ng_python_client/api/upload_api.py
restpki_ng_python_client/api/xml_signature_api.py
restpki_ng_python_client/models/__init__.py
restpki_ng_python_client/models/allocate_document_key_batch_request.py
restpki_ng_python_client/models/allocate_document_key_request.py
restpki_ng_python_client/models/attribute_certificate_model.py
restpki_ng_python_client/models/audit_package_options.py
restpki_ng_python_client/models/authentication_failures.py
restpki_ng_python_client/models/authentication_get_response.py
restpki_ng_python_client/models/authentication_post_request.py
restpki_ng_python_client/models/authentication_post_response.py
restpki_ng_python_client/models/authentications_post_request.py
restpki_ng_python_client/models/authentications_post_response.py
restpki_ng_python_client/models/authentications_post_signed_bytes_request.py
restpki_ng_python_client/models/authentications_post_signed_bytes_response.py
restpki_ng_python_client-0.9.1.1.dist-info/METADATA
restpki_ng_python_client-0.9.1.1.dist-info/WHEEL
restpki_ng_python_client-0.9.1.1.dist-info/top_level.txt
restpki_ng_python_client-0.9.1.1.dist-info/RECORD
