Metadata-Version: 2.1
Name: restpki_ng_python_client
Version: 0.9.1.1
Summary: Rest PKI Core API
Home-page: 
Author: OpenAPI Generator community
Author-email: team@openapitools.org
Keywords: OpenAPI,OpenAPI-Generator,Rest PKI Core API
Requires-Dist: urllib3 <2.1.0,>=1.24.3
Requires-Dist: python-dateutil
Requires-Dist: pydantic >=2
Requires-Dist: typing-extensions >=4.7.1
